aioshelly/__init__.py
aioshelly/common.py
aioshelly/const.py
aioshelly/exceptions.py
aioshelly/json.py
aioshelly/py.typed
aioshelly/zeroconf.py
aioshelly/ble/__init__.py
aioshelly/ble/const.py
aioshelly/ble/manufacturer_data.py
aioshelly/ble/parser.py
aioshelly/ble/provisioning.py
aioshelly/ble/backend/__init__.py
aioshelly/ble/backend/scanner.py
aioshelly/block_device/__init__.py
aioshelly/block_device/coap.py
aioshelly/block_device/device.py
aioshelly/rpc_device/__init__.py
aioshelly/rpc_device/blerpc.py
aioshelly/rpc_device/device.py
aioshelly/rpc_device/models.py
aioshelly/rpc_device/utils.py
aioshelly/rpc_device/wsrpc.py
aioshelly-13.23.1.dist-info/licenses/LICENSE
aioshelly-13.23.1.dist-info/METADATA
aioshelly-13.23.1.dist-info/WHEEL
aioshelly-13.23.1.dist-info/top_level.txt
aioshelly-13.23.1.dist-info/RECORD
