Metadata-Version: 2.4
Name: aioshelly
Version: 13.23.1
Summary: Asynchronous library to control Shelly devices.
Author-email: Paulus Schoutsen <paulus@home-assistant.io>
License-Expression: Apache-2.0
Project-URL: Source code, https://github.com/home-assistant-libs/aioshelly
Classifier: Intended Audience :: Developers
Classifier: Operating System :: OS Independent
Classifier: Programming Language :: Python
Classifier: Programming Language :: Python :: 3
Classifier: Programming Language :: Python :: 3.11
Classifier: Programming Language :: Python :: 3.12
Classifier: Programming Language :: Python :: 3.13
Classifier: Programming Language :: Python :: 3.14
Classifier: Topic :: Software Development :: Libraries :: Python Modules
Requires-Python: >=3.11
License-File: LICENSE
Requires-Dist: aiohttp>=3.11.1
Requires-Dist: bleak-retry-connector>=3.0.0
Requires-Dist: bluetooth-data-tools>=1.28.0
Requires-Dist: habluetooth>=3.42.0
Requires-Dist: orjson>=3.8.1
Requires-Dist: yarl
Requires-Dist: zeroconf>=0.148.0
Provides-Extra: lint
Requires-Dist: mypy==1.19.1; extra == "lint"
Requires-Dist: pydocstyle==6.3.0; extra == "lint"
Requires-Dist: ruff==0.14.10; extra == "lint"
Requires-Dist: types-requests; extra == "lint"
Provides-Extra: dev
Requires-Dist: aioresponses==0.7.8; extra == "dev"
Requires-Dist: pre-commit==4.5.1; extra == "dev"
Requires-Dist: pytest-asyncio==1.3.0; extra == "dev"
Requires-Dist: pytest-cov==7.0.0; extra == "dev"
Requires-Dist: pytest==9.0.2; extra == "dev"
Requires-Dist: requests; extra == "dev"
Requires-Dist: tox==4.33.0; extra == "dev"
Dynamic: license-file
